setup.py
ipynbviewer/__init__.py
ipynbviewer/__main__.py
ipynbviewer/app.py
ipynbviewer/handlers.py
ipynbviewer.egg-info/PKG-INFO
ipynbviewer.egg-info/SOURCES.txt
ipynbviewer.egg-info/dependency_links.txt
ipynbviewer.egg-info/requires.txt
ipynbviewer.egg-info/top_level.txt
ipynbviewer/static/bower.json
ipynbviewer/static/favicon.ico
ipynbviewer/static/robots.txt
ipynbviewer/static/components/Font-Awesome/css/font-awesome.css
ipynbviewer/static/components/Font-Awesome/css/font-awesome.min.css
ipynbviewer/static/components/Font-Awesome/fonts/FontAwesome.otf
ipynbviewer/static/components/Font-Awesome/fonts/fontawesome-webfont.eot
ipynbviewer/static/components/Font-Awesome/fonts/fontawesome-webfont.svg
ipynbviewer/static/components/Font-Awesome/fonts/fontawesome-webfont.ttf
ipynbviewer/static/components/Font-Awesome/fonts/fontawesome-webfont.woff
ipynbviewer/static/components/animate.css/animate.css
ipynbviewer/static/components/animate.css/animate.min.css
ipynbviewer/static/components/moment/min/moment.min.js
ipynbviewer/static/components/requirejs/README.md
ipynbviewer/static/components/requirejs/bower.json
ipynbviewer/static/components/requirejs/require.js
ipynbviewer/static/css/boilerplate.css
ipynbviewer/static/css/bootstrap-responsive.css
ipynbviewer/static/css/bootstrap-responsive.min.css
ipynbviewer/static/css/bootstrap.css
ipynbviewer/static/css/bootstrap.min.css
ipynbviewer/static/css/docs.css
ipynbviewer/static/css/jquery-ui.min.css
ipynbviewer/static/css/nbviewer.css
ipynbviewer/static/css/override.css
ipynbviewer/static/css/pygments.css
ipynbviewer/static/css/style.min.css
ipynbviewer/static/css/theme/cdp_1.css
ipynbviewer/static/css/theme/css_linalg.css
ipynbviewer/static/ico/apple-touch-icon-114-precomposed.png
ipynbviewer/static/ico/apple-touch-icon-144-precomposed.png
ipynbviewer/static/ico/apple-touch-icon-57-precomposed.png
ipynbviewer/static/ico/apple-touch-icon-72-precomposed.png
ipynbviewer/static/ico/ipynb_icon_16x16.ico
ipynbviewer/static/ico/ipynb_icon_16x16.png
ipynbviewer/static/img/Python-logo-notext.png
ipynbviewer/static/img/bird.png
ipynbviewer/static/img/github-16px.png
