Metadata-Version: 1.1
Name: ipynbviewer
Version: 0.2
Summary: Rendering local ipynb to static HTML
Home-page: https://github.com/dongweiming/ipynb-viewer
Author: Dongweiming
Author-email: ciici123@gmail.com
License: BSD
Platform: UNKNOWN
Classifier: License :: OSI Approved :: BSD License
Classifier: Programming Language :: Python :: 2
Classifier: Programming Language :: Python :: 2.7
Classifier: Programming Language :: Python :: 3
Classifier: Programming Language :: Python :: 3.3
